[
    {
      "uname": "john_doe123",
      "password": "P@ssw0rd",
      "uuid": 123456,
      "fname": "John",
      "lname": "Doe",
      "company": "Tech Solutions Inc.",
      "position": "Senior Developer",
      "email": "john.doe@example.com",
      "phone1": "0501234567",
      "phone2": "0509876543",
      "creationDate": "2019-06-15T12:00:00.000Z",
      "lastLogged": "2022-01-15T08:30:00.000Z",
      "expirationDate": "2023-04-01T00:00:00.000Z",
      "timezone": "2022-01-15T12:00:00.000Z",
      "customerStatusFields": [],
      "colorKit": 12345678
    },
    {
      "uname": "jane_smith789",
      "password": "SecureP@ss",
      "uuid": 789012,
      "fname": "Jane",
      "lname": "Smith",
      "company": "Acme Corporation",
      "position": "Software Engineer",
      "email": "jane.smith@example.com",
      "phone1": "0509876543",
      "phone2": "0501234567",
      "creationDate": "2020-02-22T10:30:00.000Z",
      "lastLogged": "2022-02-10T15:45:00.000Z",
      "expirationDate": "2024-03-01T00:00:00.000Z",
      "timezone": "2022-02-10T20:00:00.000Z",
      "customerStatusFields": [],
      "colorKit": 87654321
    },
    {
      "uname": "alice_j",
      "password": "Pa$$w0rd123",
      "uuid": 345678,
      "fname": "Alice",
      "lname": "Johnson",
      "company": "Innovate Solutions",
      "position": "Business Analyst",
      "email": "alice.johnson@example.com",
      "phone1": "0555555555",
      "phone2": "0666666666",
      "creationDate": "2021-11-07T08:00:00.000Z",
      "lastLogged": "2022-03-12T12:15:00.000Z",
      "expirationDate": "2025-04-01T00:00:00.000Z",
      "timezone": "2022-03-12T16:30:00.000Z",
      "customerStatusFields": [],
      "colorKit": 98765432
    },
    {
      "uname": "bob_w",
      "password": "BobPass123",
      "uuid": 234567,
      "fname": "Bob",
      "lname": "Williams",
      "company": "Data Innovations",
      "position": "UX Designer",
      "email": "bob.williams@example.com",
      "phone1": "0444444444",
      "phone2": "0333333333",
      "creationDate": "2022-08-01T15:45:00.000Z",
      "lastLogged": "2022-04-10T09:30:00.000Z",
      "expirationDate": "2026-05-01T00:00:00.000Z",
      "timezone": "2022-04-10T13:45:00.000Z",
      "customerStatusFields": [],
      "colorKit": 13579246
    },
    {
      "uname": "eva_m",
      "password": "EvaPass123",
      "uuid": 456789,
      "fname": "Eva",
      "lname": "Miller",
      "company": "Global Data Systems",
      "position": "Project Manager",
      "email": "eva.miller@example.com",
      "phone1": "0111111111",
      "phone2": "0222222222",
      "creationDate": "2020-12-19T12:00:00.000Z",
      "lastLogged": "2022-05-10T18:00:00.000Z",
      "expirationDate": "2022-06-01T00:00:00.000Z",
      "timezone": "2022-05-10T22:15:00.000Z",
      "customerStatusFields": [],
      "colorKit": 65432109
    }
  ]
  